pernorm/__init__.py
pernorm/per_normalizer.py
pernorm-0.0.3.dist-info/METADATA
pernorm-0.0.3.dist-info/WHEEL
pernorm-0.0.3.dist-info/top_level.txt
pernorm-0.0.3.dist-info/RECORD
